deepoptimizer/__init__.py
deepoptimizer/analyzer.py
deepoptimizer/cli.py
deepoptimizer/formatter.py
deepoptimizer/knowledge_base.py
deepoptimizer/llm_analyzer.py
deepoptimizer/prompts.py
deepoptimizer/rule_detector.py
deepoptimizer/utils.py
deepoptimizer/fixtures/additional_techniques.json
deepoptimizer/fixtures/architecture_techniques.json
deepoptimizer/fixtures/attention_techniques.json
deepoptimizer/fixtures/data_techniques.json
deepoptimizer/fixtures/distributed_techniques.json
deepoptimizer/fixtures/normalization_techniques.json
deepoptimizer/fixtures/optimizer_techniques.json
deepoptimizer/fixtures/quantization_techniques.json
deepoptimizer/fixtures/technique_relationships.json
deepoptimizer-0.1.1.dist-info/licenses/LICENSE
deepoptimizer-0.1.1.dist-info/licenses/NOTICE
deepoptimizer-0.1.1.dist-info/METADATA
deepoptimizer-0.1.1.dist-info/WHEEL
deepoptimizer-0.1.1.dist-info/entry_points.txt
deepoptimizer-0.1.1.dist-info/top_level.txt
deepoptimizer-0.1.1.dist-info/RECORD
