Metadata-Version: 2.4
Name: deepoptimizer
Version: 0.1.1
Summary: AI-powered ML code analysis and optimization suggestions
Author: Willy Nilsson
Maintainer: Willy Nilsson
License: Apache-2.0
Project-URL: Homepage, https://github.com/willynilsson/deepoptimizer
Project-URL: Documentation, https://github.com/willynilsson/deepoptimizer#readme
Project-URL: Repository, https://github.com/willynilsson/deepoptimizer
Project-URL: Issues, https://github.com/willynilsson/deepoptimizer/issues
Project-URL: Changelog, https://github.com/willynilsson/deepoptimizer/blob/main/CHANGELOG.md
Keywords: ai,optimization,machine-learning,deep-learning,code-analysis,gemini
Classifier: Development Status :: 3 - Alpha
Classifier: Intended Audience :: Developers
Classifier: Intended Audience :: Science/Research
Classifier: Operating System :: OS Independent
Classifier: Programming Language :: Python :: 3
Classifier: Programming Language :: Python :: 3.9
Classifier: Programming Language :: Python :: 3.10
Classifier: Programming Language :: Python :: 3.11
Classifier: Programming Language :: Python :: 3.12
Classifier: Topic :: Scientific/Engineering :: Artificial Intelligence
Classifier: Topic :: Software Development :: Libraries :: Python Modules
Classifier: Topic :: Software Development :: Quality Assurance
Requires-Python: >=3.9
License-File: LICENSE
License-File: NOTICE
Requires-Dist: click>=8.0.0
Requires-Dist: google-generativeai<0.4.0,>=0.3.0
Requires-Dist: rich>=13.0.0
Requires-Dist: typing-extensions>=4.0.0
Requires-Dist: python-dotenv>=1.0.0
Provides-Extra: dev
Requires-Dist: pytest>=7.0.0; extra == "dev"
Requires-Dist: pytest-cov>=4.0.0; extra == "dev"
Requires-Dist: pytest-asyncio>=0.21.0; extra == "dev"
Requires-Dist: pytest-mock>=3.10.0; extra == "dev"
Requires-Dist: black>=23.0.0; extra == "dev"
Requires-Dist: isort>=5.12.0; extra == "dev"
Requires-Dist: flake8>=6.0.0; extra == "dev"
Requires-Dist: mypy>=1.0.0; extra == "dev"
Requires-Dist: pre-commit>=3.0.0; extra == "dev"
Requires-Dist: sphinx>=6.0.0; extra == "dev"
Requires-Dist: sphinx-rtd-theme>=1.2.0; extra == "dev"
Requires-Dist: sphinx-autodoc-typehints>=1.22.0; extra == "dev"
Provides-Extra: visualization
Requires-Dist: matplotlib>=3.5.0; extra == "visualization"
Requires-Dist: seaborn>=0.12.0; extra == "visualization"
Requires-Dist: plotly>=5.14.0; extra == "visualization"
Provides-Extra: research
Requires-Dist: jupyter>=1.0.0; extra == "research"
Requires-Dist: notebook>=6.5.0; extra == "research"
Requires-Dist: ipywidgets>=8.0.0; extra == "research"
Dynamic: license-file
